ikamail/GmailHelper.py
ikamail/__init__.py
ikamail/database/__init__.py
ikamail/database/mongodb.py
ikamail-0.0.6.dist-info/LICENSE
ikamail-0.0.6.dist-info/METADATA
ikamail-0.0.6.dist-info/WHEEL
ikamail-0.0.6.dist-info/top_level.txt
ikamail-0.0.6.dist-info/RECORD
