Metadata-Version: 2.1
Name: ikamail
Version: 0.0.6
Summary: Package using to call Mail providers API
Home-page: https://gitlab.com/ikamail/ika_package.git
Author: Manitra RANAIVOHARISON
Author-email: mranaivoharison@gmail.com
License: UNKNOWN
Platform: UNKNOWN
Classifier: Programming Language :: Python :: 3
Classifier: License :: OSI Approved :: MIT License
Classifier: Operating System :: OS Independent
Requires-Python: >=3.7
Requires-Dist: google-api-python-client
Requires-Dist: google-auth-httplib2
Requires-Dist: google-auth-oauthlib
Requires-Dist: pymongo
